mathdistops/__init__.py
mathdistops/pexp.py
mathdistops/pnorm.py
mathdistops/qexp.py
mathdistops/qnorm.py
mathdistops-3.0.0.dist-info/LICENSE
mathdistops-3.0.0.dist-info/METADATA
mathdistops-3.0.0.dist-info/WHEEL
mathdistops-3.0.0.dist-info/RECORD
