Metadata-Version: 2.1
Name: mathdistops
Version: 3.0.0
Summary: This package provides function for calculating pnorm, qnorm, pexp and qexp.
License: MIT
Author: Ziwei Chen, Kun Ya,Sivakorn Oak Chong, Sandra Gross
Requires-Python: >=3.9
Classifier: License :: OSI Approved :: MIT License
Classifier: Programming Language :: Python :: 3
Classifier: Programming Language :: Python :: 3.9
Classifier: Programming Language :: Python :: 3.10
Classifier: Programming Language :: Python :: 3.11
Classifier: Programming Language :: Python :: 3.12
Requires-Dist: altair (>=5.2.0)
Requires-Dist: matplotlib (>=3.8.2)
Requires-Dist: numpy (>=1.26.3)
Requires-Dist: palmerpenguins (>=0.1.4)
Requires-Dist: pandas (>=2.1.4)
Requires-Dist: scipy (>=1.11.4)
